odoo/addons/shopfloor_cluster_picking_repack/README.rst
odoo/addons/shopfloor_cluster_picking_repack/__init__.py
odoo/addons/shopfloor_cluster_picking_repack/__manifest__.py
odoo/addons/shopfloor_cluster_picking_repack/actions/__init__.py
odoo/addons/shopfloor_cluster_picking_repack/actions/data.py
odoo/addons/shopfloor_cluster_picking_repack/actions/message.py
odoo/addons/shopfloor_cluster_picking_repack/actions/schema.py
odoo/addons/shopfloor_cluster_picking_repack/i18n/fr.po
odoo/addons/shopfloor_cluster_picking_repack/i18n/it.po
odoo/addons/shopfloor_cluster_picking_repack/i18n/shopfloor_cluster_picking_repack.pot
odoo/addons/shopfloor_cluster_picking_repack/models/__init__.py
odoo/addons/shopfloor_cluster_picking_repack/models/shopfloor_menu.py
odoo/addons/shopfloor_cluster_picking_repack/models/stock_picking.py
odoo/addons/shopfloor_cluster_picking_repack/models/stock_picking_batch.py
odoo/addons/shopfloor_cluster_picking_repack/models/stock_quant_package.py
odoo/addons/shopfloor_cluster_picking_repack/readme/CONTRIBUTORS.md
odoo/addons/shopfloor_cluster_picking_repack/readme/DESCRIPTION.md
odoo/addons/shopfloor_cluster_picking_repack/readme/USAGE.md
odoo/addons/shopfloor_cluster_picking_repack/services/__init__.py
odoo/addons/shopfloor_cluster_picking_repack/services/cluster_picking.py
odoo/addons/shopfloor_cluster_picking_repack/services/packing.py
odoo/addons/shopfloor_cluster_picking_repack/static/description/icon.png
odoo/addons/shopfloor_cluster_picking_repack/static/description/index.html
odoo/addons/shopfloor_cluster_picking_repack/tests/__init__.py
odoo/addons/shopfloor_cluster_picking_repack/tests/common.py
odoo/addons/shopfloor_cluster_picking_repack/tests/test_cluster_picking_pack_picking.py
odoo/addons/shopfloor_cluster_picking_repack/tests/test_cluster_picking_pick_pack.py
odoo/addons/shopfloor_cluster_picking_repack/tests/test_cluster_picking_unload.py
odoo/addons/shopfloor_cluster_picking_repack/views/shopfloor_menu.xml
odoo_addon_shopfloor_cluster_picking_repack-18.0.1.0.0.8.dist-info/METADATA
odoo_addon_shopfloor_cluster_picking_repack-18.0.1.0.0.8.dist-info/WHEEL
odoo_addon_shopfloor_cluster_picking_repack-18.0.1.0.0.8.dist-info/top_level.txt
odoo_addon_shopfloor_cluster_picking_repack-18.0.1.0.0.8.dist-info/RECORD
