Metadata-Version: 2.1
Name: odoo-addon-shopfloor_cluster_picking_repack
Version: 18.0.1.0.0.8
Requires-Python: >=3.10
Requires-Dist: odoo-addon-delivery_package_type_number_parcels==18.0.*
Requires-Dist: odoo-addon-internal_stock_quant_package==18.0.*
Requires-Dist: odoo-addon-shopfloor==18.0.*
Requires-Dist: odoo-addon-stock_picking_delivery_package_type_domain==18.0.*
Requires-Dist: odoo==18.0.*
Summary: Build delivery packages at the end of the cluster picking
Home-page: https://github.com/OCA/stock-logistics-shopfloor
License: AGPL-3
Author: ACSONE SA/NV,BCIM,Camptocamp,Odoo Community Association (OCA)
Author-email: support@odoo-community.org
Classifier: Programming Language :: Python
Classifier: Framework :: Odoo
Classifier: Framework :: Odoo :: 18.0
Classifier: License :: OSI Approved :: GNU Affero General Public License v3
